fewlab/__init__.py
fewlab/balanced.py
fewlab/calibration.py
fewlab/constants.py
fewlab/core.py
fewlab/design.py
fewlab/greedy.py
fewlab/hybrid.py
fewlab/py.typed
fewlab/results.py
fewlab/rowse.py
fewlab/selection.py
fewlab/utils.py
fewlab/validation.py
fewlab-1.1.1.dist-info/WHEEL
fewlab-1.1.1.dist-info/METADATA
fewlab-1.1.1.dist-info/RECORD
