Metadata-Version: 2.3
Name: fewlab
Version: 1.1.1
Summary: Pick the fewest items to label for unbiased OLS on shares
Author: Gaurav Sood
Classifier: Development Status :: 5 - Production/Stable
Classifier: Intended Audience :: Science/Research
Classifier: License :: OSI Approved :: MIT License
Classifier: Programming Language :: Python :: 3
Classifier: Programming Language :: Python :: 3.12
Classifier: Programming Language :: Python :: 3.13
Classifier: Programming Language :: Python :: 3.14
Classifier: Topic :: Scientific/Engineering :: Mathematics
Classifier: Topic :: Software Development :: Libraries :: Python Modules
Requires-Dist: numpy>=1.23
Requires-Dist: pandas>=1.5
Requires-Dist: pytest>=7.0 ; extra == 'dev'
Requires-Dist: ruff>=0.7.0 ; extra == 'dev'
Requires-Dist: pre-commit>=3.0.0 ; extra == 'dev'
Requires-Dist: mypy>=1.0 ; extra == 'dev'
Requires-Dist: sphinx>=7.0 ; extra == 'docs'
Requires-Dist: furo>=2024.7.18 ; extra == 'docs'
Requires-Dist: sphinx-autodoc-typehints>=1.25 ; extra == 'docs'
Requires-Dist: sphinx-design>=0.6.0 ; extra == 'docs'
Requires-Dist: nbsphinx>=0.9.0 ; extra == 'docs'
Requires-Dist: jupyter>=1.0 ; extra == 'docs'
Requires-Dist: ipykernel>=6.0 ; extra == 'docs'
Requires-Dist: matplotlib>=3.4 ; extra == 'docs'
Requires-Dist: seaborn>=0.11 ; extra == 'docs'
Requires-Dist: scipy>=1.7 ; extra == 'docs'
Requires-Dist: pytest>=7.0 ; extra == 'test'
Requires-Dist: pytest-cov>=4.0 ; extra == 'test'
Requires-Python: >=3.12, <3.15
Project-URL: Homepage, https://github.com/finite-sample/fewlab
Provides-Extra: dev
Provides-Extra: docs
Provides-Extra: test
